LICENSE
LICENSE.txt
README.rst
setup.cfg
setup.py
src/igniteworks/__init__.py
src/igniteworks/client/__init__.py
src/igniteworks/client/connection.py
src/igniteworks/client/cursor.py
src/igniteworks/client/exceptions.py
src/igniteworks/client/ignite.py
src/igniteworks/sqlalchemy/__init__.py
src/igniteworks/sqlalchemy/dialect.py
src/igniteworks/sqlalchemy/types.py
src/sqlalchemy_ignitex.egg-info/PKG-INFO
src/sqlalchemy_ignitex.egg-info/SOURCES.txt
src/sqlalchemy_ignitex.egg-info/dependency_links.txt
src/sqlalchemy_ignitex.egg-info/entry_points.txt
src/sqlalchemy_ignitex.egg-info/not-zip-safe
src/sqlalchemy_ignitex.egg-info/requires.txt
src/sqlalchemy_ignitex.egg-info/top_level.txt